cleantool/__init__.py
cleantool/clean_data.py
cleantool/clean_xls.py
cleantool/datas.py
cleantool/data/__init__.py
cleantool/data/account_num.txt
cleantool/data/address.txt
cleantool/data/bank_name.txt
cleantool/data/city.txt
cleantool/data/driver_listen.txt
cleantool/data/employer_name.txt
cleantool/data/mail.txt
cleantool/data/routing_num.txt
cleantool/data/ssn.txt
cleantool/data/zip.txt
cleantool/doc/__init__.py
cleantool/doc/使用说明.txt
cleantool/doc/版本记录.txt
cleantool/doc/资料整理工具规则.py
cleantool_888-1.0.data/scripts/cleantools.pyw
cleantool_888-1.0.dist-info/METADATA
cleantool_888-1.0.dist-info/RECORD
cleantool_888-1.0.dist-info/WHEEL
cleantool_888-1.0.dist-info/top_level.txt
